apitoolkit_pyramid/__init__.py
apitoolkit_pyramid-2.0.0.dist-info/METADATA
apitoolkit_pyramid-2.0.0.dist-info/WHEEL
apitoolkit_pyramid-2.0.0.dist-info/top_level.txt
apitoolkit_pyramid-2.0.0.dist-info/RECORD
