Metadata-Version: 2.1
Name: apitoolkit-pyramid
Version: 2.0.0
Summary: A Python Pyramid SDK for Apitoolkit integration
Author: APIToolkit
Author-email: hello@apitoolkit.io
Requires-Dist: pyramid
Requires-Dist: apitoolkit-common
Requires-Dist: opentelemetry-api>=1.0.0
